README.md
setup.py
gevent_jobs/__init__.py
gevent_jobs/gevent_jobs.py
gevent_jobs.egg-info/PKG-INFO
gevent_jobs.egg-info/SOURCES.txt
gevent_jobs.egg-info/dependency_links.txt
gevent_jobs.egg-info/top_level.txt