Metadata-Version: 1.0
Name: gevent-jobs
Version: 0.0.6
Summary: gevent jobs
Home-page: https://github.com/sjqzhang/gevent_jobs
Author: jqzhang
Author-email: s_jqzhang@163.com
License: MIT Licence
Keywords: pip,gevent jobs
Platform: any
